laji_auth_client/__init__.py
laji_auth_client/laji_auth_client.py
laji_auth_client-0.0.3.dist-info/LICENSE.txt
laji_auth_client-0.0.3.dist-info/METADATA
laji_auth_client-0.0.3.dist-info/WHEEL
laji_auth_client-0.0.3.dist-info/top_level.txt
laji_auth_client-0.0.3.dist-info/RECORD
