Metadata-Version: 2.1
Name: laji-auth-client
Version: 0.0.3
Summary: Python client for Laji-auth
Home-page: https://github.com/luomus/laji-auth-client-python
Author: Meeri Rannisto
Author-email: meeri.rannisto@helsinki.fi
License: MIT
License-File: LICENSE.txt
Requires-Dist: requests
